marklord.py
marklord-0.1.5.dist-info/licenses/LICENSE
marklord-0.1.5.dist-info/METADATA
marklord-0.1.5.dist-info/WHEEL
marklord-0.1.5.dist-info/entry_points.txt
marklord-0.1.5.dist-info/top_level.txt
marklord-0.1.5.dist-info/RECORD
