Metadata-Version: 2.4
Name: marklord
Version: 0.1.5
Summary: Watermarking tool for images or PDF
Author-email: phil@secdev.org
License-Expression: GPL-2.0-only
Project-URL: Repository, https://github.com/secdev/marklord/
Project-URL: Issues, https://github.com/secdev/marklord/issues
Keywords: watermark,watermarking
License-File: LICENSE
Requires-Dist: pillow
Requires-Dist: pdf2image
Requires-Dist: numpy
Dynamic: license-file
